readonly_docs_theme/__init__.py
readonly_docs_theme/context.py
readonly_docs_theme/favicon.ico
readonly_docs_theme/helpers.py
readonly_docs_theme/languages.json
readonly_docs_theme/languages.py
readonly_docs_theme/theme.pot
readonly_docs_theme/theme.py
readonly_docs_theme/extra/worker.js
readonly_docs_theme/static/jszip.js
readonly_docs_theme/static/readonly-mark.svg
readonly_docs_theme/static/readonlydocs.css
readonly_docs_theme/static/readonlydocs.js
readonly_docs_theme/static/flags/af_ZA.svg
readonly_docs_theme/static/flags/ar_SA.svg
readonly_docs_theme/static/flags/ca_ES.svg
readonly_docs_theme/static/flags/cs_CZ.svg
readonly_docs_theme/static/flags/da_DK.svg
readonly_docs_theme/static/flags/de_DE.svg
readonly_docs_theme/static/flags/el_GR.svg
readonly_docs_theme/static/flags/en.svg
readonly_docs_theme/static/flags/en_GB.svg
readonly_docs_theme/static/flags/en_PT.svg
readonly_docs_theme/static/flags/es_ES.svg
readonly_docs_theme/static/flags/fi_FI.svg
readonly_docs_theme/static/flags/fr_FR.svg
readonly_docs_theme/static/flags/he_IL.svg
readonly_docs_theme/static/flags/hu_HU.svg
readonly_docs_theme/static/flags/id_ID.svg
readonly_docs_theme/static/flags/it_IT.svg
readonly_docs_theme/static/flags/ja_JP.svg
readonly_docs_theme/static/flags/ko_KR.svg
readonly_docs_theme/static/flags/lt_LT.svg
readonly_docs_theme/static/flags/nb_NO.svg
readonly_docs_theme/static/flags/nl_NL.svg
readonly_docs_theme/static/flags/no_NO.svg
readonly_docs_theme/static/flags/pl_PL.svg
readonly_docs_theme/static/flags/pt_BR.svg
readonly_docs_theme/static/flags/pt_PT.svg
readonly_docs_theme/static/flags/ro_RO.svg
readonly_docs_theme/static/flags/ru_RU.svg
readonly_docs_theme/static/flags/sr_SP.svg
readonly_docs_theme/static/flags/sv_SE.svg
readonly_docs_theme/static/flags/tr_TR.svg
readonly_docs_theme/static/flags/uk_UA.svg
readonly_docs_theme/static/flags/vi_VN.svg
readonly_docs_theme/static/flags/zh_CN.svg
readonly_docs_theme/static/flags/zh_TW.svg
readonly_docs_theme/static/fonts/OFL.txt
readonly_docs_theme-3.0.0.dist-info/LICENSE
readonly_docs_theme-3.0.0.dist-info/METADATA
readonly_docs_theme-3.0.0.dist-info/WHEEL
readonly_docs_theme-3.0.0.dist-info/top_level.txt
readonly_docs_theme-3.0.0.dist-info/RECORD
