Metadata-Version: 2.1
Name: readonly-docs-theme
Version: 3.0.0
Summary: Theme for ReadOnly Mods documentation
Home-page: https://github.com/ReadOnlyDevelopment/readonly-docs-theme
Author: ReadOnlyDevelopment
Author-email: UNKNOWN
License: MIT
Platform: UNKNOWN
Classifier: Development Status :: 5 - Production/Stable
Classifier: License :: OSI Approved :: MIT License
Classifier: Programming Language :: Python :: 3
Classifier: Framework :: Sphinx
Classifier: Framework :: Sphinx :: Extension
Requires-Dist: sphinx-rtd-theme (==0.5.2)
